{"cameraMode":{"drawMode":0,"name":"Shaded","section":"Shading Mode"},"sceneLighting":true,"audioPlay":false,"sceneViewState":{"m_AlwaysRefresh":false,"showFog":true,"showSkybox":true,"showFlares":true,"showImageEffects":true,"showParticleSystems":true,"showVisualEffectGraphs":true,"m_FxEnabled":true},"in2DMode":false,"pivot":{"x":716.5,"y":260.25,"z":0.0},"rotation":{"x":0.07964432239532471,"y":0.041851285845041278,"z":-0.003358881687745452,"w":0.9959549903869629},"size":149.82351684570313,"orthographic":true}